[
  {
    "token_id": "113379015922744700109400673843380371641970914885846970213129353605968934558386",
    "question": "Will Haiti win the 2026 FIFA World Cup?",
    "slug": "will-haiti-win-the-2026-fifa-world-cup",
    "regime": "carry_no",
    "direction": "NO",
    "confidence": 0.71,
    "position": "medium",
    "quality": 0.7,
    "risk_score": 0.25,
    "reasons": [
      "ultra low YES price",
      "better classified as carry_no than trend",
      "stale low-vol carry_no",
      "deep-tail World Cup outright",
      "cluster=world_cup"
    ],
    "risk_flags": [
      "stale_carry_no",
      "deep_tail_world_cup",
      "cooldown_active"
    ],
    "advisory_flags": [
      "stale_carry_no",
      "deep_tail_world_cup",
      "cooldown_active"
    ],
    "blocking_flags": [
      "stale_carry_no",
      "deep_tail_world_cup"
    ],
    "yes_price": 0.0015,
    "no_price": 0.9985,
    "liquidity": 6057952.58,
    "volume": 16242598.54,
    "chg_1h": 0.0,
    "chg_4h": 0.0,
    "chg_24h": 0.0,
    "chg_7d": 0.0,
    "latest_ts": "2026-05-01T13:00:04",
    "features": {
      "token_id": "113379015922744700109400673843380371641970914885846970213129353605968934558386",
      "question": "Will Haiti win the 2026 FIFA World Cup?",
      "slug": "will-haiti-win-the-2026-fifa-world-cup",
      "yes_price": 0.0015,
      "no_price": 0.9985,
      "liquidity": 6057952.57817,
      "volume": 16242598.541820062,
      "latest_ts": "2026-05-01T13:00:04",
      "history_points": 10886,
      "chg_1h": 0.0,
      "chg_4h": 0.0,
      "chg_24h": 0.0,
      "chg_7d": 0.0,
      "rsi_14": 3.868818995548125,
      "volatility": 0.0,
      "trend_slope_4h": 0.0,
      "trend_slope_24h": 0.0,
      "pct_rank_7d": 0.9859917223814072,
      "pct_rank_30d": 0.9959581113356605,
      "noise_score": 0.0,
      "hours_to_event": 1906.9988888888888,
      "event_time": "2026-07-20",
      "spread": null
    },
    "cluster": "world_cup"
  },
  {
    "token_id": "33747305042007778221968790541070114008811587676172030120559423448386310500957",
    "question": "Will Iran win the 2026 FIFA World Cup?",
    "slug": "will-iran-win-the-2026-fifa-world-cup-788",
    "regime": "carry_no",
    "direction": "NO",
    "confidence": 0.71,
    "position": "medium",
    "quality": 0.7,
    "risk_score": 0.25,
    "reasons": [
      "ultra low YES price",
      "better classified as carry_no than trend",
      "deep-tail World Cup outright",
      "cluster=world_cup"
    ],
    "risk_flags": [
      "deep_tail_world_cup",
      "cooldown_active"
    ],
    "advisory_flags": [
      "deep_tail_world_cup",
      "cooldown_active"
    ],
    "blocking_flags": [
      "deep_tail_world_cup"
    ],
    "yes_price": 0.0015,
    "no_price": 0.9985,
    "liquidity": 5785981.77,
    "volume": 22050298.92,
    "chg_1h": 0.0,
    "chg_4h": 0.0,
    "chg_24h": 0.0,
    "chg_7d": 0.0,
    "latest_ts": "2026-05-01T13:00:04",
    "features": {
      "token_id": "33747305042007778221968790541070114008811587676172030120559423448386310500957",
      "question": "Will Iran win the 2026 FIFA World Cup?",
      "slug": "will-iran-win-the-2026-fifa-world-cup-788",
      "yes_price": 0.0015,
      "no_price": 0.9985,
      "liquidity": 5785981.77031,
      "volume": 22050298.92279006,
      "latest_ts": "2026-05-01T13:00:04",
      "history_points": 10886,
      "chg_1h": 0.0,
      "chg_4h": 0.0,
      "chg_24h": 0.0,
      "chg_7d": 0.0,
      "rsi_14": 2.596633027406341,
      "volatility": 0.0,
      "trend_slope_4h": 0.0,
      "trend_slope_24h": 0.0,
      "pct_rank_7d": 0.9843998726520217,
      "pct_rank_30d": 0.3171963990446445,
      "noise_score": 0.0,
      "hours_to_event": 1906.9988888888888,
      "event_time": "2026-07-20",
      "spread": null
    },
    "cluster": "world_cup"
  },
  {
    "token_id": "43907673646206657865778036957293730446366626078011238443367990170655175896145",
    "question": "Will Ghana win the 2026 FIFA World Cup?",
    "slug": "will-ghana-win-the-2026-fifa-world-cup",
    "regime": "carry_no",
    "direction": "NO",
    "confidence": 0.71,
    "position": "medium",
    "quality": 0.7,
    "risk_score": 0.25,
    "reasons": [
      "ultra low YES price",
      "better classified as carry_no than trend",
      "stale low-vol carry_no",
      "deep-tail World Cup outright",
      "cluster=world_cup"
    ],
    "risk_flags": [
      "stale_carry_no",
      "deep_tail_world_cup",
      "cooldown_active"
    ],
    "advisory_flags": [
      "stale_carry_no",
      "deep_tail_world_cup",
      "cooldown_active"
    ],
    "blocking_flags": [
      "stale_carry_no",
      "deep_tail_world_cup"
    ],
    "yes_price": 0.0025,
    "no_price": 0.9975,
    "liquidity": 5678809.22,
    "volume": 16050163.81,
    "chg_1h": 0.0,
    "chg_4h": 0.0,
    "chg_24h": 0.0,
    "chg_7d": 0.0,
    "latest_ts": "2026-05-01T13:00:04",
    "features": {
      "token_id": "43907673646206657865778036957293730446366626078011238443367990170655175896145",
      "question": "Will Ghana win the 2026 FIFA World Cup?",
      "slug": "will-ghana-win-the-2026-fifa-world-cup",
      "yes_price": 0.0025,
      "no_price": 0.9975,
      "liquidity": 5678809.22463,
      "volume": 16050163.809010904,
      "latest_ts": "2026-05-01T13:00:04",
      "history_points": 10886,
      "chg_1h": 0.0,
      "chg_4h": 0.0,
      "chg_24h": 0.0,
      "chg_7d": 0.0,
      "rsi_14": 18.64389237451391,
      "volatility": 0.0,
      "trend_slope_4h": 0.0,
      "trend_slope_24h": 0.0,
      "pct_rank_7d": 0.9843998726520217,
      "pct_rank_30d": 0.9954988058056219,
      "noise_score": 0.0,
      "hours_to_event": 1906.9988888888888,
      "event_time": "2026-07-20",
      "spread": null
    },
    "cluster": "world_cup"
  },
  {
    "token_id": "23542782083949026234898323432000742558288032327930681121040136746492993951914",
    "question": "Will Saudi Arabia win the 2026 FIFA World Cup?",
    "slug": "will-saudi-arabia-win-the-2026-fifa-world-cup",
    "regime": "carry_no",
    "direction": "NO",
    "confidence": 0.71,
    "position": "medium",
    "quality": 0.7,
    "risk_score": 0.25,
    "reasons": [
      "ultra low YES price",
      "better classified as carry_no than trend",
      "stale low-vol carry_no",
      "deep-tail World Cup outright",
      "cluster=world_cup"
    ],
    "risk_flags": [
      "stale_carry_no",
      "deep_tail_world_cup",
      "cooldown_active"
    ],
    "advisory_flags": [
      "stale_carry_no",
      "deep_tail_world_cup",
      "cooldown_active"
    ],
    "blocking_flags": [
      "stale_carry_no",
      "deep_tail_world_cup"
    ],
    "yes_price": 0.0025,
    "no_price": 0.9975,
    "liquidity": 5616195.36,
    "volume": 24862690.86,
    "chg_1h": 0.0,
    "chg_4h": 0.0,
    "chg_24h": 0.0,
    "chg_7d": 0.0,
    "latest_ts": "2026-05-01T13:00:04",
    "features": {
      "token_id": "23542782083949026234898323432000742558288032327930681121040136746492993951914",
      "question": "Will Saudi Arabia win the 2026 FIFA World Cup?",
      "slug": "will-saudi-arabia-win-the-2026-fifa-world-cup",
      "yes_price": 0.0025,
      "no_price": 0.9975,
      "liquidity": 5616195.35926,
      "volume": 24862690.86256449,
      "latest_ts": "2026-05-01T13:00:04",
      "history_points": 10886,
      "chg_1h": 0.0,
      "chg_4h": 0.0,
      "chg_24h": 0.0,
      "chg_7d": 0.0,
      "rsi_14": 32.308283418784555,
      "volatility": 0.0,
      "trend_slope_4h": 0.0,
      "trend_slope_24h": 0.0,
      "pct_rank_7d": 0.9843998726520217,
      "pct_rank_30d": 0.9954988058056219,
      "noise_score": 0.0,
      "hours_to_event": 1906.9988888888888,
      "event_time": "2026-07-20",
      "spread": null
    },
    "cluster": "world_cup"
  },
  {
    "token_id": "93165696161088512376930999170413968261015485018106746563527821398897374023845",
    "question": "Will Paraguay win the 2026 FIFA World Cup?",
    "slug": "will-paraguay-win-the-2026-fifa-world-cup-967",
    "regime": "carry_no",
    "direction": "NO",
    "confidence": 0.71,
    "position": "medium",
    "quality": 0.7,
    "risk_score": 0.25,
    "reasons": [
      "ultra low YES price",
      "better classified as carry_no than trend",
      "stale low-vol carry_no",
      "deep-tail World Cup outright",
      "cluster=world_cup"
    ],
    "risk_flags": [
      "stale_carry_no",
      "deep_tail_world_cup",
      "cooldown_active"
    ],
    "advisory_flags": [
      "stale_carry_no",
      "deep_tail_world_cup",
      "cooldown_active"
    ],
    "blocking_flags": [
      "stale_carry_no",
      "deep_tail_world_cup"
    ],
    "yes_price": 0.0045,
    "no_price": 0.9955,
    "liquidity": 5449546.7,
    "volume": 17411421.36,
    "chg_1h": 0.0,
    "chg_4h": 0.0,
    "chg_24h": 0.0,
    "chg_7d": 0.0,
    "latest_ts": "2026-05-01T13:00:04",
    "features": {
      "token_id": "93165696161088512376930999170413968261015485018106746563527821398897374023845",
      "question": "Will Paraguay win the 2026 FIFA World Cup?",
      "slug": "will-paraguay-win-the-2026-fifa-world-cup-967",
      "yes_price": 0.0045,
      "no_price": 0.9955,
      "liquidity": 5449546.69823,
      "volume": 17411421.357444383,
      "latest_ts": "2026-05-01T13:00:04",
      "history_points": 10886,
      "chg_1h": 0.0,
      "chg_4h": 0.0,
      "chg_24h": 0.0,
      "chg_7d": 0.0,
      "rsi_14": 2.6112033254592433,
      "volatility": 0.0,
      "trend_slope_4h": 0.0,
      "trend_slope_24h": 0.0,
      "pct_rank_7d": 0.9843998726520217,
      "pct_rank_30d": 0.9954988058056219,
      "noise_score": 0.0,
      "hours_to_event": 1906.9988888888888,
      "event_time": "2026-07-20",
      "spread": null
    },
    "cluster": "world_cup"
  },
  {
    "token_id": "105252206997885252352889070218074909957179496257006510170583432513037465278006",
    "question": "Will Scotland win the 2026 FIFA World Cup?",
    "slug": "will-scotland-win-the-2026-fifa-world-cup",
    "regime": "carry_no",
    "direction": "NO",
    "confidence": 0.71,
    "position": "medium",
    "quality": 0.7,
    "risk_score": 0.25,
    "reasons": [
      "ultra low YES price",
      "better classified as carry_no than trend",
      "stale low-vol carry_no",
      "deep-tail World Cup outright",
      "cluster=world_cup"
    ],
    "risk_flags": [
      "stale_carry_no",
      "deep_tail_world_cup",
      "cooldown_active"
    ],
    "advisory_flags": [
      "stale_carry_no",
      "deep_tail_world_cup",
      "cooldown_active"
    ],
    "blocking_flags": [
      "stale_carry_no",
      "deep_tail_world_cup"
    ],
    "yes_price": 0.0035,
    "no_price": 0.9965,
    "liquidity": 4987382.34,
    "volume": 16713551.91,
    "chg_1h": 0.0,
    "chg_4h": 0.0,
    "chg_24h": 0.0,
    "chg_7d": 0.0,
    "latest_ts": "2026-05-01T13:00:04",
    "features": {
      "token_id": "105252206997885252352889070218074909957179496257006510170583432513037465278006",
      "question": "Will Scotland win the 2026 FIFA World Cup?",
      "slug": "will-scotland-win-the-2026-fifa-world-cup",
      "yes_price": 0.0035,
      "no_price": 0.9965,
      "liquidity": 4987382.33598,
      "volume": 16713551.905954193,
      "latest_ts": "2026-05-01T13:00:04",
      "history_points": 10886,
      "chg_1h": 0.0,
      "chg_4h": 0.0,
      "chg_24h": 0.0,
      "chg_7d": 0.0,
      "rsi_14": 2.6540790073972147,
      "volatility": 0.0,
      "trend_slope_4h": 0.0,
      "trend_slope_24h": 0.0,
      "pct_rank_7d": 0.9843998726520217,
      "pct_rank_30d": 0.9954988058056219,
      "noise_score": 0.0,
      "hours_to_event": 1906.9988888888888,
      "event_time": "2026-07-20",
      "spread": null
    },
    "cluster": "world_cup"
  },
  {
    "token_id": "97239126062673310243763617236644392945530356142765650402171508075574679292913",
    "question": "Will Uruguay win the 2026 FIFA World Cup?",
    "slug": "will-uruguay-win-the-2026-fifa-world-cup-932",
    "regime": "carry_no",
    "direction": "NO",
    "confidence": 0.71,
    "position": "medium",
    "quality": 0.7,
    "risk_score": 0.25,
    "reasons": [
      "ultra low YES price",
      "better classified as carry_no than trend",
      "stale low-vol carry_no",
      "cluster=world_cup"
    ],
    "risk_flags": [
      "stale_carry_no",
      "cooldown_active"
    ],
    "advisory_flags": [
      "stale_carry_no",
      "cooldown_active"
    ],
    "blocking_flags": [
      "stale_carry_no"
    ],
    "yes_price": 0.0105,
    "no_price": 0.9895,
    "liquidity": 3543676.02,
    "volume": 14951297.56,
    "chg_1h": 0.0,
    "chg_4h": 0.0,
    "chg_24h": 0.0,
    "chg_7d": 0.0,
    "latest_ts": "2026-05-01T13:00:04",
    "features": {
      "token_id": "97239126062673310243763617236644392945530356142765650402171508075574679292913",
      "question": "Will Uruguay win the 2026 FIFA World Cup?",
      "slug": "will-uruguay-win-the-2026-fifa-world-cup-932",
      "yes_price": 0.0105,
      "no_price": 0.9895,
      "liquidity": 3543676.01546,
      "volume": 14951297.559137806,
      "latest_ts": "2026-05-01T13:00:04",
      "history_points": 10886,
      "chg_1h": 0.0,
      "chg_4h": 0.0,
      "chg_24h": 0.0,
      "chg_7d": 0.0,
      "rsi_14": 27.84398890327529,
      "volatility": 0.0,
      "trend_slope_4h": 0.0,
      "trend_slope_24h": 0.0,
      "pct_rank_7d": 0.9828080229226361,
      "pct_rank_30d": 0.9950395002755833,
      "noise_score": 0.0,
      "hours_to_event": 1906.9988888888888,
      "event_time": "2026-07-20",
      "spread": null
    },
    "cluster": "world_cup"
  },
  {
    "token_id": "55087250670040717711131370018408221134109122974378698780636020561523521220754",
    "question": "Will Kim Kardashian win the 2028 Democratic presidential nomination?",
    "slug": "will-kim-kardashian-win-the-2028-democratic-presidential-nomination",
    "regime": "carry_no",
    "direction": "NO",
    "confidence": 0.71,
    "position": "medium",
    "quality": 0.7,
    "risk_score": 0.25,
    "reasons": [
      "ultra low YES price",
      "better classified as carry_no than trend",
      "stale low-vol carry_no",
      "cluster=us_election"
    ],
    "risk_flags": [
      "stale_carry_no",
      "cooldown_active"
    ],
    "advisory_flags": [
      "stale_carry_no",
      "cooldown_active"
    ],
    "blocking_flags": [
      "stale_carry_no"
    ],
    "yes_price": 0.0065,
    "no_price": 0.9935,
    "liquidity": 2955830.3,
    "volume": 38764686.39,
    "chg_1h": 0.0,
    "chg_4h": 0.0,
    "chg_24h": 0.0,
    "chg_7d": 0.0,
    "latest_ts": "2026-05-01T13:00:04",
    "features": {
      "token_id": "55087250670040717711131370018408221134109122974378698780636020561523521220754",
      "question": "Will Kim Kardashian win the 2028 Democratic presidential nomination?",
      "slug": "will-kim-kardashian-win-the-2028-democratic-presidential-nomination",
      "yes_price": 0.0065,
      "no_price": 0.9935,
      "liquidity": 2955830.30301,
      "volume": 38764686.38937837,
      "latest_ts": "2026-05-01T13:00:04",
      "history_points": 10886,
      "chg_1h": 0.0,
      "chg_4h": 0.0,
      "chg_24h": 0.0,
      "chg_7d": 0.0,
      "rsi_14": 2.587770922554057,
      "volatility": 0.0,
      "trend_slope_4h": 0.0,
      "trend_slope_24h": 0.0,
      "pct_rank_7d": 0.9843998726520217,
      "pct_rank_30d": 0.9954988058056219,
      "noise_score": 0.0,
      "hours_to_event": 22090.998888888887,
      "event_time": "2028-11-07",
      "spread": null
    },
    "cluster": "us_election"
  },
  {
    "token_id": "18704778540677036028551740861729937822696511439974613107767625408338509619395",
    "question": "Will Turkiye win the 2026 FIFA World Cup?",
    "slug": "will-turkiye-win-the-2026-fifa-world-cup",
    "regime": "carry_no",
    "direction": "NO",
    "confidence": 0.71,
    "position": "medium",
    "quality": 0.7,
    "risk_score": 0.25,
    "reasons": [
      "ultra low YES price",
      "better classified as carry_no than trend",
      "cluster=world_cup"
    ],
    "risk_flags": [
      "cooldown_active"
    ],
    "advisory_flags": [
      "cooldown_active"
    ],
    "blocking_flags": [],
    "yes_price": 0.0065,
    "no_price": 0.9935,
    "liquidity": 2916211.89,
    "volume": 7999063.14,
    "chg_1h": 0.0,
    "chg_4h": 0.0,
    "chg_24h": 0.0,
    "chg_7d": 0.0,
    "latest_ts": "2026-05-01T13:00:04",
    "features": {
      "token_id": "18704778540677036028551740861729937822696511439974613107767625408338509619395",
      "question": "Will Turkiye win the 2026 FIFA World Cup?",
      "slug": "will-turkiye-win-the-2026-fifa-world-cup",
      "yes_price": 0.0065,
      "no_price": 0.9935,
      "liquidity": 2916211.88523,
      "volume": 7999063.143923018,
      "latest_ts": "2026-05-01T13:00:04",
      "history_points": 10886,
      "chg_1h": 0.0,
      "chg_4h": 0.0,
      "chg_24h": 0.0,
      "chg_7d": 0.0,
      "rsi_14": 2.654435193865055,
      "volatility": 0.0,
      "trend_slope_4h": 0.0,
      "trend_slope_24h": 0.0,
      "pct_rank_7d": 0.9843998726520217,
      "pct_rank_30d": 0.44359728091126216,
      "noise_score": 0.0,
      "hours_to_event": 1906.9988888888888,
      "event_time": "2026-07-20",
      "spread": null
    },
    "cluster": "world_cup"
  },
  {
    "token_id": "98803390175521456712653678280474920637934596234667490983228578374641217211132",
    "question": "Will Colombia win the 2026 FIFA World Cup?",
    "slug": "will-colombia-win-the-2026-fifa-world-cup-734",
    "regime": "carry_no",
    "direction": "NO",
    "confidence": 0.71,
    "position": "medium",
    "quality": 0.7,
    "risk_score": 0.25,
    "reasons": [
      "ultra low YES price",
      "better classified as carry_no than trend",
      "cluster=world_cup"
    ],
    "risk_flags": [
      "cooldown_active"
    ],
    "advisory_flags": [
      "cooldown_active"
    ],
    "blocking_flags": [],
    "yes_price": 0.0165,
    "no_price": 0.9835,
    "liquidity": 2851226.18,
    "volume": 13580341.13,
    "chg_1h": 0.0,
    "chg_4h": 0.0,
    "chg_24h": -0.029411764705882377,
    "chg_7d": 0.0,
    "latest_ts": "2026-05-01T13:00:04",
    "features": {
      "token_id": "98803390175521456712653678280474920637934596234667490983228578374641217211132",
      "question": "Will Colombia win the 2026 FIFA World Cup?",
      "slug": "will-colombia-win-the-2026-fifa-world-cup-734",
      "yes_price": 0.0165,
      "no_price": 0.9835,
      "liquidity": 2851226.17883,
      "volume": 13580341.127310717,
      "latest_ts": "2026-05-01T13:00:04",
      "history_points": 10886,
      "chg_1h": 0.0,
      "chg_4h": 0.0,
      "chg_24h": -0.029411764705882377,
      "chg_7d": 0.0,
      "rsi_14": 2.59775244580878,
      "volatility": 0.0,
      "trend_slope_4h": 0.0,
      "trend_slope_24h": 0.0,
      "pct_rank_7d": 0.9815345431391277,
      "pct_rank_30d": 0.9188866433951864,
      "noise_score": 0.0,
      "hours_to_event": 1906.9988888888888,
      "event_time": "2026-07-20",
      "spread": null
    },
    "cluster": "world_cup"
  },
  {
    "token_id": "81633484456710374417231462107666791993850637546563366185897100962157481970040",
    "question": "Will Phil Murphy win the 2028 Democratic presidential nomination?",
    "slug": "will-phil-murphy-win-the-2028-democratic-presidential-nomination-611",
    "regime": "carry_no",
    "direction": "NO",
    "confidence": 0.71,
    "position": "medium",
    "quality": 0.7,
    "risk_score": 0.25,
    "reasons": [
      "ultra low YES price",
      "better classified as carry_no than trend",
      "stale low-vol carry_no",
      "cluster=us_election"
    ],
    "risk_flags": [
      "stale_carry_no",
      "cooldown_active"
    ],
    "advisory_flags": [
      "stale_carry_no",
      "cooldown_active"
    ],
    "blocking_flags": [
      "stale_carry_no"
    ],
    "yes_price": 0.0065,
    "no_price": 0.9935,
    "liquidity": 2492299.14,
    "volume": 38671569.87,
    "chg_1h": 0.0,
    "chg_4h": 0.0,
    "chg_24h": 0.0,
    "chg_7d": 0.0,
    "latest_ts": "2026-05-01T13:00:04",
    "features": {
      "token_id": "81633484456710374417231462107666791993850637546563366185897100962157481970040",
      "question": "Will Phil Murphy win the 2028 Democratic presidential nomination?",
      "slug": "will-phil-murphy-win-the-2028-democratic-presidential-nomination-611",
      "yes_price": 0.0065,
      "no_price": 0.9935,
      "liquidity": 2492299.14269,
      "volume": 38671569.87244065,
      "latest_ts": "2026-05-01T13:00:04",
      "history_points": 10886,
      "chg_1h": 0.0,
      "chg_4h": 0.0,
      "chg_24h": 0.0,
      "chg_7d": 0.0,
      "rsi_14": 2.5798780858577004,
      "volatility": 0.0,
      "trend_slope_4h": 0.0,
      "trend_slope_24h": 0.0,
      "pct_rank_7d": 0.9843998726520217,
      "pct_rank_30d": 0.9954988058056219,
      "noise_score": 0.0,
      "hours_to_event": 22090.998888888887,
      "event_time": "2028-11-07",
      "spread": null
    },
    "cluster": "us_election"
  },
  {
    "token_id": "62131913648515148266463816694306031394539656598501514114816028349608560215534",
    "question": "Will Switzerland win the 2026 FIFA World Cup?",
    "slug": "will-switzerland-win-the-2026-fifa-world-cup",
    "regime": "carry_no",
    "direction": "NO",
    "confidence": 0.71,
    "position": "medium",
    "quality": 0.7,
    "risk_score": 0.25,
    "reasons": [
      "ultra low YES price",
      "better classified as carry_no than trend",
      "cluster=world_cup"
    ],
    "risk_flags": [
      "cooldown_active"
    ],
    "advisory_flags": [
      "cooldown_active"
    ],
    "blocking_flags": [],
    "yes_price": 0.0095,
    "no_price": 0.9905,
    "liquidity": 2445081.03,
    "volume": 14166149.5,
    "chg_1h": 0.0,
    "chg_4h": 0.0,
    "chg_24h": 0.0,
    "chg_7d": 0.0,
    "latest_ts": "2026-05-01T13:00:04",
    "features": {
      "token_id": "62131913648515148266463816694306031394539656598501514114816028349608560215534",
      "question": "Will Switzerland win the 2026 FIFA World Cup?",
      "slug": "will-switzerland-win-the-2026-fifa-world-cup",
      "yes_price": 0.0095,
      "no_price": 0.9905,
      "liquidity": 2445081.03384,
      "volume": 14166149.499987325,
      "latest_ts": "2026-05-01T13:00:04",
      "history_points": 10886,
      "chg_1h": 0.0,
      "chg_4h": 0.0,
      "chg_24h": 0.0,
      "chg_7d": 0.0,
      "rsi_14": 2.8717329789707833,
      "volatility": 0.0,
      "trend_slope_4h": 0.0,
      "trend_slope_24h": 0.0,
      "pct_rank_7d": 0.9843998726520217,
      "pct_rank_30d": 0.9213668932573948,
      "noise_score": 0.0,
      "hours_to_event": 1906.9988888888888,
      "event_time": "2026-07-20",
      "spread": null
    },
    "cluster": "world_cup"
  },
  {
    "token_id": "22587775301869146748237913050505932485648958481571808324285560650057390882036",
    "question": "Will Mexico win the 2026 FIFA World Cup?",
    "slug": "will-mexico-win-the-2026-fifa-world-cup-529",
    "regime": "carry_no",
    "direction": "NO",
    "confidence": 0.71,
    "position": "medium",
    "quality": 0.7,
    "risk_score": 0.25,
    "reasons": [
      "ultra low YES price",
      "better classified as carry_no than trend",
      "cluster=world_cup"
    ],
    "risk_flags": [
      "cooldown_active"
    ],
    "advisory_flags": [
      "cooldown_active"
    ],
    "blocking_flags": [],
    "yes_price": 0.0105,
    "no_price": 0.9895,
    "liquidity": 2403252.32,
    "volume": 16251341.68,
    "chg_1h": 0.0,
    "chg_4h": 0.0,
    "chg_24h": 0.0,
    "chg_7d": 0.0,
    "latest_ts": "2026-05-01T13:00:04",
    "features": {
      "token_id": "22587775301869146748237913050505932485648958481571808324285560650057390882036",
      "question": "Will Mexico win the 2026 FIFA World Cup?",
      "slug": "will-mexico-win-the-2026-fifa-world-cup-529",
      "yes_price": 0.0105,
      "no_price": 0.9895,
      "liquidity": 2403252.32062,
      "volume": 16251341.67708017,
      "latest_ts": "2026-05-01T13:00:04",
      "history_points": 10886,
      "chg_1h": 0.0,
      "chg_4h": 0.0,
      "chg_24h": 0.0,
      "chg_7d": 0.0,
      "rsi_14": 3.869893195864563,
      "volatility": 0.0,
      "trend_slope_4h": 0.0,
      "trend_slope_24h": 0.0,
      "pct_rank_7d": 0.9859917223814072,
      "pct_rank_30d": 0.6604813521954804,
      "noise_score": 0.0,
      "hours_to_event": 1906.9988888888888,
      "event_time": "2026-07-20",
      "spread": null
    },
    "cluster": "world_cup"
  },
  {
    "token_id": "11343337042526652606304508556838778144915122118685013460142819817079620240439",
    "question": "Will Hunter Biden win the 2028 Democratic presidential nomination?",
    "slug": "will-person-a-win-the-2028-democratic-presidential-nomination",
    "regime": "carry_no",
    "direction": "NO",
    "confidence": 0.71,
    "position": "medium",
    "quality": 0.7,
    "risk_score": 0.25,
    "reasons": [
      "ultra low YES price",
      "better classified as carry_no than trend",
      "stale low-vol carry_no",
      "cluster=us_election"
    ],
    "risk_flags": [
      "stale_carry_no",
      "cooldown_active"
    ],
    "advisory_flags": [
      "stale_carry_no",
      "cooldown_active"
    ],
    "blocking_flags": [
      "stale_carry_no"
    ],
    "yes_price": 0.0065,
    "no_price": 0.9935,
    "liquidity": 2312742.52,
    "volume": 34337386.68,
    "chg_1h": 0.0,
    "chg_4h": 0.0,
    "chg_24h": 0.0,
    "chg_7d": 0.0,
    "latest_ts": "2026-05-01T13:00:04",
    "features": {
      "token_id": "11343337042526652606304508556838778144915122118685013460142819817079620240439",
      "question": "Will Hunter Biden win the 2028 Democratic presidential nomination?",
      "slug": "will-person-a-win-the-2028-democratic-presidential-nomination",
      "yes_price": 0.0065,
      "no_price": 0.9935,
      "liquidity": 2312742.52462,
      "volume": 34337386.67692968,
      "latest_ts": "2026-05-01T13:00:04",
      "history_points": 10886,
      "chg_1h": 0.0,
      "chg_4h": 0.0,
      "chg_24h": 0.0,
      "chg_7d": 0.0,
      "rsi_14": 2.6079806844866766,
      "volatility": 0.0,
      "trend_slope_4h": 0.0,
      "trend_slope_24h": 0.0,
      "pct_rank_7d": 0.9843998726520217,
      "pct_rank_30d": 0.9954988058056219,
      "noise_score": 0.0,
      "hours_to_event": 22090.998888888887,
      "event_time": "2028-11-07",
      "spread": null
    },
    "cluster": "us_election"
  },
  {
    "token_id": "35165603539035270209469650915267170915291414186795231160733227083640059691764",
    "question": "Will Gina Raimondo win the 2028 Democratic presidential nomination?",
    "slug": "will-gina-raimondo-win-the-2028-democratic-presidential-nomination-676",
    "regime": "carry_no",
    "direction": "NO",
    "confidence": 0.71,
    "position": "medium",
    "quality": 0.7,
    "risk_score": 0.25,
    "reasons": [
      "ultra low YES price",
      "better classified as carry_no than trend",
      "stale low-vol carry_no",
      "cluster=us_election"
    ],
    "risk_flags": [
      "stale_carry_no",
      "cooldown_active"
    ],
    "advisory_flags": [
      "stale_carry_no",
      "cooldown_active"
    ],
    "blocking_flags": [
      "stale_carry_no"
    ],
    "yes_price": 0.0065,
    "no_price": 0.9935,
    "liquidity": 2201284.05,
    "volume": 30972919.43,
    "chg_1h": 0.0,
    "chg_4h": 0.0,
    "chg_24h": 0.0,
    "chg_7d": 0.0,
    "latest_ts": "2026-05-01T13:00:04",
    "features": {
      "token_id": "35165603539035270209469650915267170915291414186795231160733227083640059691764",
      "question": "Will Gina Raimondo win the 2028 Democratic presidential nomination?",
      "slug": "will-gina-raimondo-win-the-2028-democratic-presidential-nomination-676",
      "yes_price": 0.0065,
      "no_price": 0.9935,
      "liquidity": 2201284.05222,
      "volume": 30972919.42941998,
      "latest_ts": "2026-05-01T13:00:04",
      "history_points": 10886,
      "chg_1h": 0.0,
      "chg_4h": 0.0,
      "chg_24h": 0.0,
      "chg_7d": 0.0,
      "rsi_14": 13.4849969640062,
      "volatility": 0.0,
      "trend_slope_4h": 0.0,
      "trend_slope_24h": 0.0,
      "pct_rank_7d": 0.9843998726520217,
      "pct_rank_30d": 0.9954988058056219,
      "noise_score": 0.0,
      "hours_to_event": 22090.998888888887,
      "event_time": "2028-11-07",
      "spread": null
    },
    "cluster": "us_election"
  },
  {
    "token_id": "30815807067456631524510535002617106205417832891402132396713720656146245200000",
    "question": "Will Belgium win the 2026 FIFA World Cup?",
    "slug": "will-belgium-win-the-2026-fifa-world-cup-358",
    "regime": "carry_no",
    "direction": "NO",
    "confidence": 0.71,
    "position": "medium",
    "quality": 0.7,
    "risk_score": 0.25,
    "reasons": [
      "ultra low YES price",
      "better classified as carry_no than trend",
      "cluster=world_cup"
    ],
    "risk_flags": [
      "cooldown_active"
    ],
    "advisory_flags": [
      "cooldown_active"
    ],
    "blocking_flags": [],
    "yes_price": 0.0195,
    "no_price": 0.9805,
    "liquidity": 2182101.33,
    "volume": 14782190.86,
    "chg_1h": 0.0,
    "chg_4h": 0.0,
    "chg_24h": 0.0,
    "chg_7d": -0.04878048780487809,
    "latest_ts": "2026-05-01T13:00:04",
    "features": {
      "token_id": "30815807067456631524510535002617106205417832891402132396713720656146245200000",
      "question": "Will Belgium win the 2026 FIFA World Cup?",
      "slug": "will-belgium-win-the-2026-fifa-world-cup-358",
      "yes_price": 0.0195,
      "no_price": 0.9805,
      "liquidity": 2182101.32824,
      "volume": 14782190.861390105,
      "latest_ts": "2026-05-01T13:00:04",
      "history_points": 10886,
      "chg_1h": 0.0,
      "chg_4h": 0.0,
      "chg_24h": 0.0,
      "chg_7d": -0.04878048780487809,
      "rsi_14": 8.895870222648156,
      "volatility": 0.0,
      "trend_slope_4h": 0.0,
      "trend_slope_24h": 0.0,
      "pct_rank_7d": 0.28303088188475006,
      "pct_rank_30d": 0.697868822340621,
      "noise_score": 0.0,
      "hours_to_event": 1906.9988888888888,
      "event_time": "2026-07-20",
      "spread": null
    },
    "cluster": "world_cup"
  },
  {
    "token_id": "88927218779847397120407909832537568114340511586397698395193736044476021744522",
    "question": "Will Barack Obama win the 2028 Democratic presidential nomination?",
    "slug": "will-barack-obama-win-the-2028-democratic-presidential-nomination-265",
    "regime": "carry_no",
    "direction": "NO",
    "confidence": 0.71,
    "position": "medium",
    "quality": 0.7,
    "risk_score": 0.25,
    "reasons": [
      "ultra low YES price",
      "better classified as carry_no than trend",
      "stale low-vol carry_no",
      "cluster=us_election"
    ],
    "risk_flags": [
      "stale_carry_no",
      "cooldown_active"
    ],
    "advisory_flags": [
      "stale_carry_no",
      "cooldown_active"
    ],
    "blocking_flags": [
      "stale_carry_no"
    ],
    "yes_price": 0.0075,
    "no_price": 0.9925,
    "liquidity": 2018895.06,
    "volume": 29044545.0,
    "chg_1h": 0.0,
    "chg_4h": 0.0,
    "chg_24h": 0.0,
    "chg_7d": 0.0,
    "latest_ts": "2026-05-01T13:00:04",
    "features": {
      "token_id": "88927218779847397120407909832537568114340511586397698395193736044476021744522",
      "question": "Will Barack Obama win the 2028 Democratic presidential nomination?",
      "slug": "will-barack-obama-win-the-2028-democratic-presidential-nomination-265",
      "yes_price": 0.0075,
      "no_price": 0.9925,
      "liquidity": 2018895.0566,
      "volume": 29044544.997799747,
      "latest_ts": "2026-05-01T13:00:04",
      "history_points": 10886,
      "chg_1h": 0.0,
      "chg_4h": 0.0,
      "chg_24h": 0.0,
      "chg_7d": 0.0,
      "rsi_14": 2.593248071868956,
      "volatility": 0.0,
      "trend_slope_4h": 0.0,
      "trend_slope_24h": 0.0,
      "pct_rank_7d": 0.9843998726520217,
      "pct_rank_30d": 0.9954988058056219,
      "noise_score": 0.0,
      "hours_to_event": 22090.998888888887,
      "event_time": "2028-11-07",
      "spread": null
    },
    "cluster": "us_election"
  },
  {
    "token_id": "106572879185916710503631021854572801471104977091252507745096331167318654083650",
    "question": "Will the Phoenix Suns win the 2026 NBA Finals?",
    "slug": "will-the-phoenix-suns-win-the-2026-nba-finals",
    "regime": "carry_no",
    "direction": "NO",
    "confidence": 0.71,
    "position": "medium",
    "quality": 0.7,
    "risk_score": 0.25,
    "reasons": [
      "ultra low YES price",
      "better classified as carry_no than trend",
      "cluster=other"
    ],
    "risk_flags": [
      "cooldown_active"
    ],
    "advisory_flags": [
      "cooldown_active"
    ],
    "blocking_flags": [],
    "yes_price": 0.0005,
    "no_price": 0.9995,
    "liquidity": 1990116.29,
    "volume": 17570704.05,
    "chg_1h": 0.0,
    "chg_4h": 0.0,
    "chg_24h": 0.0,
    "chg_7d": -0.6666666666666666,
    "latest_ts": "2026-04-28T16:15:03",
    "features": {
      "token_id": "106572879185916710503631021854572801471104977091252507745096331167318654083650",
      "question": "Will the Phoenix Suns win the 2026 NBA Finals?",
      "slug": "will-the-phoenix-suns-win-the-2026-nba-finals",
      "yes_price": 0.0005,
      "no_price": 0.9995,
      "liquidity": 1990116.2899,
      "volume": 17570704.051959917,
      "latest_ts": "2026-04-28T16:15:03",
      "history_points": 9973,
      "chg_1h": 0.0,
      "chg_4h": 0.0,
      "chg_24h": 0.0,
      "chg_7d": -0.6666666666666666,
      "rsi_14": 0.0,
      "volatility": 0.0,
      "trend_slope_4h": 0.0,
      "trend_slope_24h": 0.0,
      "pct_rank_7d": 0.8336906584992343,
      "pct_rank_30d": 0.2729369297102176,
      "noise_score": 0.0,
      "hours_to_event": 1519.7491666666667,
      "event_time": "2026-07-01",
      "spread": null
    },
    "cluster": "other"
  },
  {
    "token_id": "104464678880204778606895232389511543522030897731392516718349574106843434770446",
    "question": "Will Tim Walz win the 2028 Democratic presidential nomination?",
    "slug": "will-tim-walz-win-the-2028-democratic-presidential-nomination-475",
    "regime": "carry_no",
    "direction": "NO",
    "confidence": 0.71,
    "position": "medium",
    "quality": 0.7,
    "risk_score": 0.25,
    "reasons": [
      "ultra low YES price",
      "better classified as carry_no than trend",
      "cluster=us_election"
    ],
    "risk_flags": [
      "cooldown_active"
    ],
    "advisory_flags": [
      "cooldown_active"
    ],
    "blocking_flags": [],
    "yes_price": 0.0065,
    "no_price": 0.9935,
    "liquidity": 1896942.29,
    "volume": 39421252.86,
    "chg_1h": 0.0,
    "chg_4h": 0.0,
    "chg_24h": 0.0,
    "chg_7d": -0.13333333333333333,
    "latest_ts": "2026-05-01T13:00:04",
    "features": {
      "token_id": "104464678880204778606895232389511543522030897731392516718349574106843434770446",
      "question": "Will Tim Walz win the 2028 Democratic presidential nomination?",
      "slug": "will-tim-walz-win-the-2028-democratic-presidential-nomination-475",
      "yes_price": 0.0065,
      "no_price": 0.9935,
      "liquidity": 1896942.29407,
      "volume": 39421252.861441866,
      "latest_ts": "2026-05-01T13:00:04",
      "history_points": 10886,
      "chg_1h": 0.0,
      "chg_4h": 0.0,
      "chg_24h": 0.0,
      "chg_7d": -0.13333333333333333,
      "rsi_14": 2.5798780858577004,
      "volatility": 0.0,
      "trend_slope_4h": 0.0,
      "trend_slope_24h": 0.0,
      "pct_rank_7d": 0.979624323463865,
      "pct_rank_30d": 0.3238103986772001,
      "noise_score": 0.0,
      "hours_to_event": 22090.998888888887,
      "event_time": "2028-11-07",
      "spread": null
    },
    "cluster": "us_election"
  },
  {
    "token_id": "58378309871183461257693288827678410871907006920578755035402846056315798427503",
    "question": "Will Mark Cuban win the 2028 Democratic presidential nomination?",
    "slug": "will-mark-cuban-win-the-2028-democratic-presidential-nomination-329",
    "regime": "carry_no",
    "direction": "NO",
    "confidence": 0.71,
    "position": "medium",
    "quality": 0.7,
    "risk_score": 0.25,
    "reasons": [
      "ultra low YES price",
      "better classified as carry_no than trend",
      "cluster=us_election"
    ],
    "risk_flags": [
      "cooldown_active"
    ],
    "advisory_flags": [
      "cooldown_active"
    ],
    "blocking_flags": [],
    "yes_price": 0.0095,
    "no_price": 0.9905,
    "liquidity": 1849862.03,
    "volume": 21374824.62,
    "chg_1h": 0.0,
    "chg_4h": 0.0,
    "chg_24h": 0.0,
    "chg_7d": -0.09523809523809532,
    "latest_ts": "2026-05-01T13:00:04",
    "features": {
      "token_id": "58378309871183461257693288827678410871907006920578755035402846056315798427503",
      "question": "Will Mark Cuban win the 2028 Democratic presidential nomination?",
      "slug": "will-mark-cuban-win-the-2028-democratic-presidential-nomination-329",
      "yes_price": 0.0095,
      "no_price": 0.9905,
      "liquidity": 1849862.03313,
      "volume": 21374824.616893284,
      "latest_ts": "2026-05-01T13:00:04",
      "history_points": 10886,
      "chg_1h": 0.0,
      "chg_4h": 0.0,
      "chg_24h": 0.0,
      "chg_7d": -0.09523809523809532,
      "rsi_14": 2.599811243128187,
      "volatility": 0.0,
      "trend_slope_4h": 0.0,
      "trend_slope_24h": 0.0,
      "pct_rank_7d": 0.8643744030563515,
      "pct_rank_30d": 0.44515891971339333,
      "noise_score": 0.0,
      "hours_to_event": 22090.998888888887,
      "event_time": "2028-11-07",
      "spread": null
    },
    "cluster": "us_election"
  },
  {
    "token_id": "85111524713956582520646495718683425629132278867496750899986579388014440159452",
    "question": "Will Cooper Flagg win the 2025–26 NBA Rookie of the Year award?",
    "slug": "will-cooper-flagg-win-the-202526-nba-rookie-of-the-year-award",
    "regime": "trend",
    "direction": "YES",
    "confidence": 0.69,
    "position": "medium",
    "quality": 0.675,
    "risk_score": 0.25,
    "reasons": [
      "4h move visible",
      "24h move strong",
      "7d move strong",
      "24h and 7d aligned",
      "liquidity good",
      "cluster=other"
    ],
    "risk_flags": [
      "cooldown_active"
    ],
    "advisory_flags": [
      "cooldown_active"
    ],
    "blocking_flags": [],
    "yes_price": 0.9995,
    "no_price": 0.0005,
    "liquidity": 596311.69,
    "volume": 938347.74,
    "chg_1h": 0.0,
    "chg_4h": 0.2370049504950495,
    "chg_24h": 0.2509386733416771,
    "chg_7d": 0.42480399144689956,
    "latest_ts": "2026-04-28T11:10:00",
    "features": {
      "token_id": "85111524713956582520646495718683425629132278867496750899986579388014440159452",
      "question": "Will Cooper Flagg win the 2025–26 NBA Rookie of the Year award?",
      "slug": "will-cooper-flagg-win-the-202526-nba-rookie-of-the-year-award",
      "yes_price": 0.9995,
      "no_price": 0.0005,
      "liquidity": 596311.69407,
      "volume": 938347.7372940008,
      "latest_ts": "2026-04-28T11:10:00",
      "history_points": 9739,
      "chg_1h": 0.0,
      "chg_4h": 0.2370049504950495,
      "chg_24h": 0.2509386733416771,
      "chg_7d": 0.42480399144689956,
      "rsi_14": 98.83422305268539,
      "volatility": 0.0,
      "trend_slope_4h": 0.0,
      "trend_slope_24h": 0.0002742316990270769,
      "pct_rank_7d": 1.0,
      "pct_rank_30d": 1.0,
      "noise_score": 0.0,
      "hours_to_event": 468.8333333333333,
      "event_time": "2026-05-18",
      "spread": null
    },
    "cluster": "other"
  },
  {
    "token_id": "70663352401606372246362604193214664065595751757222752105245221905399175050480",
    "question": "Will Kamala Harris win the 2028 US Presidential Election?",
    "slug": "will-kamala-harris-win-the-2028-us-presidential-election",
    "regime": "trend",
    "direction": "YES",
    "confidence": 0.69,
    "position": "medium",
    "quality": 0.675,
    "risk_score": 0.25,
    "reasons": [
      "4h move visible",
      "24h move strong",
      "7d move strong",
      "24h and 7d aligned",
      "liquidity good",
      "cluster=us_election"
    ],
    "risk_flags": [
      "cooldown_active"
    ],
    "advisory_flags": [
      "cooldown_active"
    ],
    "blocking_flags": [],
    "yes_price": 0.0505,
    "no_price": 0.9495,
    "liquidity": 124472.89,
    "volume": 7211514.61,
    "chg_1h": 0.0,
    "chg_4h": 0.03061224489795921,
    "chg_24h": 0.3466666666666668,
    "chg_7d": 0.24691358024691362,
    "latest_ts": "2026-05-01T13:02:00",
    "features": {
      "token_id": "70663352401606372246362604193214664065595751757222752105245221905399175050480",
      "question": "Will Kamala Harris win the 2028 US Presidential Election?",
      "slug": "will-kamala-harris-win-the-2028-us-presidential-election",
      "yes_price": 0.0505,
      "no_price": 0.9495,
      "liquidity": 124472.89241,
      "volume": 7211514.605842007,
      "latest_ts": "2026-05-01T13:02:00",
      "history_points": 10888,
      "chg_1h": 0.0,
      "chg_4h": 0.03061224489795921,
      "chg_24h": 0.3466666666666668,
      "chg_7d": 0.24691358024691362,
      "rsi_14": 99.9808195612046,
      "volatility": 0.0,
      "trend_slope_4h": 0.0,
      "trend_slope_24h": 3.753920327807634e-06,
      "pct_rank_7d": 0.9844097995545658,
      "pct_rank_30d": 0.9954996326230713,
      "noise_score": 0.0,
      "hours_to_event": 22090.966666666667,
      "event_time": "2028-11-07",
      "spread": null
    },
    "cluster": "us_election"
  },
  {
    "token_id": "11807691644868166983390207408868795383945915035851758101409310535538572683733",
    "question": "Will Donald Trump win the 2028 US Presidential Election?",
    "slug": "will-donald-trump-win-the-2028-us-presidential-election",
    "regime": "mean_revert",
    "direction": "NO",
    "confidence": 0.664,
    "position": "medium",
    "quality": 0.66,
    "risk_score": 0.32,
    "reasons": [
      "upper percentile fade setup",
      "RSI extreme",
      "24h move extended",
      "vNext gate: question_blocklisted_v6",
      "cluster=us_election"
    ],
    "risk_flags": [
      "question_blocklisted_v6",
      "cooldown_active"
    ],
    "advisory_flags": [
      "question_blocklisted_v6",
      "cooldown_active"
    ],
    "blocking_flags": [
      "question_blocklisted_v6"
    ],
    "yes_price": 0.034,
    "no_price": 0.966,
    "liquidity": 308584.43,
    "volume": 7601366.7,
    "chg_1h": 0.0,
    "chg_4h": -0.11688311688311681,
    "chg_24h": 0.25925925925925936,
    "chg_7d": 0.0,
    "latest_ts": "2026-05-01T13:01:03",
    "features": {
      "token_id": "11807691644868166983390207408868795383945915035851758101409310535538572683733",
      "question": "Will Donald Trump win the 2028 US Presidential Election?",
      "slug": "will-donald-trump-win-the-2028-us-presidential-election",
      "yes_price": 0.034,
      "no_price": 0.966,
      "liquidity": 308584.42576,
      "volume": 7601366.698608188,
      "latest_ts": "2026-05-01T13:01:03",
      "history_points": 10887,
      "chg_1h": 0.0,
      "chg_4h": -0.11688311688311681,
      "chg_24h": 0.25925925925925936,
      "chg_7d": 0.0,
      "rsi_14": 0.0054128704100975256,
      "volatility": 0.001471436344325026,
      "trend_slope_4h": -5.699287589051373e-06,
      "trend_slope_24h": 1.6456152225073824e-05,
      "pct_rank_7d": 0.9045194143857416,
      "pct_rank_30d": 0.8785707724809406,
      "noise_score": 0.0,
      "hours_to_event": 22090.9825,
      "event_time": "2028-11-07",
      "spread": null
    },
    "cluster": "us_election"
  },
  {
    "token_id": "71169839497420596285841847514123589847893415750912355173877524195175834054354",
    "question": "Will Josh Shapiro win the 2028 Democratic presidential nomination?",
    "slug": "will-josh-shapiro-win-the-2028-democratic-presidential-nomination-977",
    "regime": "mean_revert",
    "direction": "NO",
    "confidence": 0.664,
    "position": "medium",
    "quality": 0.66,
    "risk_score": 0.32,
    "reasons": [
      "upper percentile fade setup",
      "RSI extreme",
      "24h move extended",
      "vNext gate: question_blocklisted_v6",
      "cluster=us_election"
    ],
    "risk_flags": [
      "question_blocklisted_v6",
      "cooldown_active"
    ],
    "advisory_flags": [
      "question_blocklisted_v6",
      "cooldown_active"
    ],
    "blocking_flags": [
      "question_blocklisted_v6"
    ],
    "yes_price": 0.0405,
    "no_price": 0.9595,
    "liquidity": 241587.16,
    "volume": 7511066.27,
    "chg_1h": 0.0,
    "chg_4h": 0.0,
    "chg_24h": 0.09459459459459468,
    "chg_7d": 0.10958904109589052,
    "latest_ts": "2026-05-01T13:01:03",
    "features": {
      "token_id": "71169839497420596285841847514123589847893415750912355173877524195175834054354",
      "question": "Will Josh Shapiro win the 2028 Democratic presidential nomination?",
      "slug": "will-josh-shapiro-win-the-2028-democratic-presidential-nomination-977",
      "yes_price": 0.0405,
      "no_price": 0.9595,
      "liquidity": 241587.15572,
      "volume": 7511066.271512223,
      "latest_ts": "2026-05-01T13:01:03",
      "history_points": 10887,
      "chg_1h": 0.0,
      "chg_4h": 0.0,
      "chg_24h": 0.09459459459459468,
      "chg_7d": 0.10958904109589052,
      "rsi_14": 3.989352403990992,
      "volatility": 0.0,
      "trend_slope_4h": 0.0,
      "trend_slope_24h": 0.0,
      "pct_rank_7d": 0.9844048376830045,
      "pct_rank_30d": 0.9307430880867089,
      "noise_score": 0.0,
      "hours_to_event": 22090.9825,
      "event_time": "2028-11-07",
      "spread": null
    },
    "cluster": "us_election"
  },
  {
    "token_id": "8113830512143065501177519557124858581375945005490796772950589720955457782465",
    "question": "Will Alexandria Ocasio-Cortez win the 2028 US Presidential Election?",
    "slug": "will-alexandria-ocasio-cortez-win-the-2028-us-presidential-election",
    "regime": "mean_revert",
    "direction": "YES",
    "confidence": 0.664,
    "position": "medium",
    "quality": 0.66,
    "risk_score": 0.32,
    "reasons": [
      "lower percentile bounce setup",
      "RSI extreme",
      "24h move extended",
      "vNext gate: question_blocklisted_v6",
      "cluster=us_election"
    ],
    "risk_flags": [
      "high_noise",
      "question_blocklisted_v6",
      "cooldown_active"
    ],
    "advisory_flags": [
      "high_noise",
      "question_blocklisted_v6",
      "cooldown_active"
    ],
    "blocking_flags": [
      "high_noise",
      "question_blocklisted_v6"
    ],
    "yes_price": 0.0555,
    "no_price": 0.9445,
    "liquidity": 158988.77,
    "volume": 11301863.95,
    "chg_1h": 0.0,
    "chg_4h": -0.09016393442622948,
    "chg_24h": -0.0347826086956522,
    "chg_7d": -0.06722689075630246,
    "latest_ts": "2026-05-01T13:01:03",
    "features": {
      "token_id": "8113830512143065501177519557124858581375945005490796772950589720955457782465",
      "question": "Will Alexandria Ocasio-Cortez win the 2028 US Presidential Election?",
      "slug": "will-alexandria-ocasio-cortez-win-the-2028-us-presidential-election",
      "yes_price": 0.0555,
      "no_price": 0.9445,
      "liquidity": 158988.76555,
      "volume": 11301863.950508803,
      "latest_ts": "2026-05-01T13:01:03",
      "history_points": 10887,
      "chg_1h": 0.0,
      "chg_4h": -0.09016393442622948,
      "chg_24h": -0.0347826086956522,
      "chg_7d": -0.06722689075630246,
      "rsi_14": 9.746547577933185,
      "volatility": 0.0025777626508625144,
      "trend_slope_4h": 4.679415073115863e-06,
      "trend_slope_24h": -8.760498694990345e-06,
      "pct_rank_7d": 0.03214513049013367,
      "pct_rank_30d": 0.46909157711031507,
      "noise_score": 6.855654600401044,
      "hours_to_event": 22090.9825,
      "event_time": "2028-11-07",
      "spread": null
    },
    "cluster": "us_election"
  },
  {
    "token_id": "70071592420137476676935286377781779672157004436137616627487590484756055232944",
    "question": "Will Jon Ossoff win the 2028 Democratic presidential nomination?",
    "slug": "will-jon-ossoff-win-the-2028-democratic-presidential-nomination-885",
    "regime": "mean_revert",
    "direction": "NO",
    "confidence": 0.664,
    "position": "medium",
    "quality": 0.66,
    "risk_score": 0.32,
    "reasons": [
      "upper percentile fade setup",
      "RSI extreme",
      "24h move extended",
      "vNext gate: question_blocklisted_v6",
      "cluster=us_election"
    ],
    "risk_flags": [
      "question_blocklisted_v6",
      "cooldown_active"
    ],
    "advisory_flags": [
      "question_blocklisted_v6",
      "cooldown_active"
    ],
    "blocking_flags": [
      "question_blocklisted_v6"
    ],
    "yes_price": 0.0665,
    "no_price": 0.9335,
    "liquidity": 127410.46,
    "volume": 10923277.93,
    "chg_1h": 0.0,
    "chg_4h": 0.015267175572519097,
    "chg_24h": 0.13675213675213674,
    "chg_7d": 0.13675213675213674,
    "latest_ts": "2026-05-01T13:02:00",
    "features": {
      "token_id": "70071592420137476676935286377781779672157004436137616627487590484756055232944",
      "question": "Will Jon Ossoff win the 2028 Democratic presidential nomination?",
      "slug": "will-jon-ossoff-win-the-2028-democratic-presidential-nomination-885",
      "yes_price": 0.0665,
      "no_price": 0.9335,
      "liquidity": 127410.45529,
      "volume": 10923277.926780915,
      "latest_ts": "2026-05-01T13:02:00",
      "history_points": 10888,
      "chg_1h": 0.0,
      "chg_4h": 0.015267175572519097,
      "chg_24h": 0.13675213675213674,
      "chg_7d": 0.13675213675213674,
      "rsi_14": 99.99999999999973,
      "volatility": 0.0,
      "trend_slope_4h": 0.0,
      "trend_slope_24h": 1.4590450828105728e-06,
      "pct_rank_7d": 0.986000636334712,
      "pct_rank_30d": 0.9527920646583394,
      "noise_score": 0.0,
      "hours_to_event": 22090.966666666667,
      "event_time": "2028-11-07",
      "spread": null
    },
    "cluster": "us_election"
  },
  {
    "token_id": "101738487887518832481587379955535423775326921556438741919099866785354159699479",
    "question": "Will the Colorado Avalanche win the 2026 NHL Stanley Cup?",
    "slug": "will-the-colorado-avalanche-win-the-2026-nhl-stanley-cup",
    "regime": "mean_revert",
    "direction": "NO",
    "confidence": 0.664,
    "position": "medium",
    "quality": 0.66,
    "risk_score": 0.32,
    "reasons": [
      "upper percentile fade setup",
      "RSI extreme",
      "24h move extended",
      "vNext gate: liquidity_below_vnext_min",
      "cluster=other"
    ],
    "risk_flags": [
      "liquidity_below_vnext_min",
      "cooldown_active"
    ],
    "advisory_flags": [
      "liquidity_below_vnext_min",
      "cooldown_active"
    ],
    "blocking_flags": [
      "liquidity_below_vnext_min"
    ],
    "yes_price": 0.3095,
    "no_price": 0.6905,
    "liquidity": 80510.52,
    "volume": 13930149.34,
    "chg_1h": 0.0,
    "chg_4h": 0.006504065040650413,
    "chg_24h": 0.03511705685618732,
    "chg_7d": 0.19038461538461535,
    "latest_ts": "2026-05-01T13:02:00",
    "features": {
      "token_id": "101738487887518832481587379955535423775326921556438741919099866785354159699479",
      "question": "Will the Colorado Avalanche win the 2026 NHL Stanley Cup?",
      "slug": "will-the-colorado-avalanche-win-the-2026-nhl-stanley-cup",
      "yes_price": 0.3095,
      "no_price": 0.6905,
      "liquidity": 80510.5243,
      "volume": 13930149.335140059,
      "latest_ts": "2026-05-01T13:02:00",
      "history_points": 10888,
      "chg_1h": 0.0,
      "chg_4h": 0.006504065040650413,
      "chg_24h": 0.03511705685618732,
      "chg_7d": 0.19038461538461535,
      "rsi_14": 99.99844004503461,
      "volatility": 0.0,
      "trend_slope_4h": 0.0,
      "trend_slope_24h": 4.525053008274138e-06,
      "pct_rank_7d": 0.9891823098950048,
      "pct_rank_30d": 0.9968772961058046,
      "noise_score": 0.0,
      "hours_to_event": 1426.9666666666667,
      "event_time": "2026-06-30",
      "spread": null
    },
    "cluster": "other"
  },
  {
    "token_id": "52393600221905688380980180540161090876971894580569515967716227210336633318551",
    "question": "Will the Minnesota Wild win the 2026 NHL Stanley Cup?",
    "slug": "will-the-minnesota-wild-win-the-2026-nhl-stanley-cup",
    "regime": "mean_revert",
    "direction": "NO",
    "confidence": 0.664,
    "position": "medium",
    "quality": 0.66,
    "risk_score": 0.32,
    "reasons": [
      "upper percentile fade setup",
      "RSI extreme",
      "24h move extended",
      "vNext gate: liquidity_below_vnext_min",
      "cluster=other"
    ],
    "risk_flags": [
      "high_noise",
      "liquidity_below_vnext_min",
      "cooldown_active"
    ],
    "advisory_flags": [
      "high_noise",
      "liquidity_below_vnext_min",
      "cooldown_active"
    ],
    "blocking_flags": [
      "high_noise",
      "liquidity_below_vnext_min"
    ],
    "yes_price": 0.0735,
    "no_price": 0.9265,
    "liquidity": 56248.99,
    "volume": 9011562.98,
    "chg_1h": -0.16477272727272727,
    "chg_4h": 0.13953488372093015,
    "chg_24h": -0.85,
    "chg_7d": 1.6727272727272726,
    "latest_ts": "2026-05-01T13:02:00",
    "features": {
      "token_id": "52393600221905688380980180540161090876971894580569515967716227210336633318551",
      "question": "Will the Minnesota Wild win the 2026 NHL Stanley Cup?",
      "slug": "will-the-minnesota-wild-win-the-2026-nhl-stanley-cup",
      "yes_price": 0.0735,
      "no_price": 0.9265,
      "liquidity": 56248.98645,
      "volume": 9011562.980502935,
      "latest_ts": "2026-05-01T13:02:00",
      "history_points": 10888,
      "chg_1h": -0.16477272727272727,
      "chg_4h": 0.13953488372093015,
      "chg_24h": -0.85,
      "chg_7d": 1.6727272727272726,
      "rsi_14": 25.996744714778984,
      "volatility": 0.0157218927180834,
      "trend_slope_4h": -0.00015201713067116606,
      "trend_slope_24h": 2.3390818831968347e-05,
      "pct_rank_7d": 0.948456888323258,
      "pct_rank_30d": 0.9842027920646583,
      "noise_score": 3.232167320774593,
      "hours_to_event": 1426.9666666666667,
      "event_time": "2026-06-30",
      "spread": null
    },
    "cluster": "other"
  },
  {
    "token_id": "35573117698117780238142713946749692621043319879346349609080985768472429209643",
    "question": "Will the Tampa Bay Lightning win the 2026 NHL Stanley Cup?",
    "slug": "will-the-tampa-bay-lightning-win-the-2026-nhl-stanley-cup",
    "regime": "mean_revert",
    "direction": "YES",
    "confidence": 0.664,
    "position": "medium",
    "quality": 0.66,
    "risk_score": 0.32,
    "reasons": [
      "lower percentile bounce setup",
      "RSI extreme",
      "24h move extended",
      "vNext gate: liquidity_below_vnext_min",
      "cluster=other"
    ],
    "risk_flags": [
      "liquidity_below_vnext_min",
      "cooldown_active"
    ],
    "advisory_flags": [
      "liquidity_below_vnext_min",
      "cooldown_active"
    ],
    "blocking_flags": [
      "liquidity_below_vnext_min"
    ],
    "yes_price": 0.041,
    "no_price": 0.959,
    "liquidity": 31556.71,
    "volume": 1898334.5,
    "chg_1h": 0.0,
    "chg_4h": -0.012048192771084347,
    "chg_24h": -0.3109243697478991,
    "chg_7d": -0.6238532110091743,
    "latest_ts": "2026-05-01T13:02:00",
    "features": {
      "token_id": "35573117698117780238142713946749692621043319879346349609080985768472429209643",
      "question": "Will the Tampa Bay Lightning win the 2026 NHL Stanley Cup?",
      "slug": "will-the-tampa-bay-lightning-win-the-2026-nhl-stanley-cup",
      "yes_price": 0.041,
      "no_price": 0.959,
      "liquidity": 31556.71156,
      "volume": 1898334.4974999707,
      "latest_ts": "2026-05-01T13:02:00",
      "history_points": 10888,
      "chg_1h": 0.0,
      "chg_4h": -0.012048192771084347,
      "chg_24h": -0.3109243697478991,
      "chg_7d": -0.6238532110091743,
      "rsi_14": 0.00016182630955086097,
      "volatility": 0.0,
      "trend_slope_4h": 0.0,
      "trend_slope_24h": 1.1283139377604134e-06,
      "pct_rank_7d": 0.09163219853643016,
      "pct_rank_30d": 0.02645113886847906,
      "noise_score": 0.0,
      "hours_to_event": 1426.9666666666667,
      "event_time": "2026-06-30",
      "spread": null
    },
    "cluster": "other"
  },
  {
    "token_id": "98022490269692409998126496127597032490334070080325855126491859374983463996227",
    "question": "New Rihanna Album before GTA VI?",
    "slug": "new-rhianna-album-before-gta-vi-926",
    "regime": "mean_revert",
    "direction": "YES",
    "confidence": 0.664,
    "position": "medium",
    "quality": 0.66,
    "risk_score": 0.32,
    "reasons": [
      "lower percentile bounce setup",
      "RSI extreme",
      "24h move extended",
      "vNext gate: question_blocklisted_v6",
      "cluster=gta_vi"
    ],
    "risk_flags": [
      "question_blocklisted_v6",
      "cooldown_active"
    ],
    "advisory_flags": [
      "question_blocklisted_v6",
      "cooldown_active"
    ],
    "blocking_flags": [
      "question_blocklisted_v6"
    ],
    "yes_price": 0.515,
    "no_price": 0.485,
    "liquidity": 24605.29,
    "volume": 705350.56,
    "chg_1h": -0.009615384615384623,
    "chg_4h": -0.10434782608695643,
    "chg_24h": 0.030000000000000027,
    "chg_7d": -0.20155038759689922,
    "latest_ts": "2026-05-01T13:02:00",
    "features": {
      "token_id": "98022490269692409998126496127597032490334070080325855126491859374983463996227",
      "question": "New Rihanna Album before GTA VI?",
      "slug": "new-rhianna-album-before-gta-vi-926",
      "yes_price": 0.515,
      "no_price": 0.485,
      "liquidity": 24605.2936,
      "volume": 705350.5610250012,
      "latest_ts": "2026-05-01T13:02:00",
      "history_points": 10888,
      "chg_1h": -0.009615384615384623,
      "chg_4h": -0.10434782608695643,
      "chg_24h": 0.030000000000000027,
      "chg_7d": -0.20155038759689922,
      "rsi_14": 3.765709858782884e-05,
      "volatility": 0.0009762414207541037,
      "trend_slope_4h": -5.744399137607801e-05,
      "trend_slope_24h": -8.571666595662603e-05,
      "pct_rank_7d": 0.028953229398663696,
      "pct_rank_30d": 0.008357825128581926,
      "noise_score": 0.0,
      "hours_to_event": 2170.9666666666667,
      "event_time": "2026-07-31",
      "spread": null
    },
    "cluster": "gta_vi"
  },
  {
    "token_id": "102227184035967850089766981958743064457339118173548431660886438726896222843254",
    "question": "Will the San Antonio Spurs win the 2026 NBA Finals?",
    "slug": "will-the-san-antonio-spurs-win-the-2026-nba-finals",
    "regime": "trend",
    "direction": "YES",
    "confidence": 0.66,
    "position": "medium",
    "quality": 0.675,
    "risk_score": 0.4,
    "reasons": [
      "4h move visible",
      "24h move strong",
      "7d move strong",
      "24h and 7d aligned",
      "4h and 24h slope aligned",
      "liquidity good",
      "cluster=other"
    ],
    "risk_flags": [
      "high_noise",
      "trend_noisy",
      "cooldown_active"
    ],
    "advisory_flags": [
      "high_noise",
      "trend_noisy",
      "cooldown_active"
    ],
    "blocking_flags": [
      "high_noise",
      "trend_noisy"
    ],
    "yes_price": 0.1855,
    "no_price": 0.8145,
    "liquidity": 284198.51,
    "volume": 25000181.1,
    "chg_1h": 0.05698005698005704,
    "chg_4h": 0.11411411411411404,
    "chg_24h": 0.1630094043887147,
    "chg_7d": 0.6343612334801761,
    "latest_ts": "2026-05-01T13:01:03",
    "features": {
      "token_id": "102227184035967850089766981958743064457339118173548431660886438726896222843254",
      "question": "Will the San Antonio Spurs win the 2026 NBA Finals?",
      "slug": "will-the-san-antonio-spurs-win-the-2026-nba-finals",
      "yes_price": 0.1855,
      "no_price": 0.8145,
      "liquidity": 284198.50931,
      "volume": 25000181.103874754,
      "latest_ts": "2026-05-01T13:01:03",
      "history_points": 10887,
      "chg_1h": 0.05698005698005704,
      "chg_4h": 0.11411411411411404,
      "chg_24h": 0.1630094043887147,
      "chg_7d": 0.6343612334801761,
      "rsi_14": 99.99999999999264,
      "volatility": 0.0037032710900468226,
      "trend_slope_4h": 0.00010102737157855274,
      "trend_slope_24h": 1.840035253958048e-05,
      "pct_rank_7d": 0.9891788669637174,
      "pct_rank_30d": 0.9909065858363185,
      "noise_score": 4.426762458634466,
      "hours_to_event": 1450.9825,
      "event_time": "2026-07-01",
      "spread": null
    },
    "cluster": "other"
  },
  {
    "token_id": "32338220190071351435772801779725302244575775216413325951443816017994629993401",
    "question": "Xi Jinping out before 2027?",
    "slug": "xi-jinping-out-before-2027",
    "regime": "trend",
    "direction": "YES",
    "confidence": 0.66,
    "position": "medium",
    "quality": 0.675,
    "risk_score": 0.4,
    "reasons": [
      "4h move visible",
      "24h move strong",
      "7d move strong",
      "24h and 7d aligned",
      "liquidity good",
      "cluster=other"
    ],
    "risk_flags": [
      "high_noise",
      "trend_noisy",
      "cooldown_active"
    ],
    "advisory_flags": [
      "high_noise",
      "trend_noisy",
      "cooldown_active"
    ],
    "blocking_flags": [
      "high_noise",
      "trend_noisy"
    ],
    "yes_price": 0.0825,
    "no_price": 0.9175,
    "liquidity": 265327.97,
    "volume": 8659278.33,
    "chg_1h": -0.05714285714285704,
    "chg_4h": -0.046242774566473875,
    "chg_24h": 0.13793103448275876,
    "chg_7d": 0.2595419847328244,
    "latest_ts": "2026-05-01T13:01:03",
    "features": {
      "token_id": "32338220190071351435772801779725302244575775216413325951443816017994629993401",
      "question": "Xi Jinping out before 2027?",
      "slug": "xi-jinping-out-before-2027",
      "yes_price": 0.0825,
      "no_price": 0.9175,
      "liquidity": 265327.97481,
      "volume": 8659278.325540727,
      "latest_ts": "2026-05-01T13:01:03",
      "history_points": 10887,
      "chg_1h": -0.05714285714285704,
      "chg_4h": -0.046242774566473875,
      "chg_24h": 0.13793103448275876,
      "chg_7d": 0.2595419847328244,
      "rsi_14": 0.09640748505849217,
      "volatility": 0.004030626389632485,
      "trend_slope_4h": -7.478815148106482e-05,
      "trend_slope_24h": 1.5111067158860954e-05,
      "pct_rank_7d": 0.6947803946530872,
      "pct_rank_30d": 0.9119132910811059,
      "noise_score": 4.443994469669094,
      "hours_to_event": 5842.9825,
      "event_time": "2026-12-31",
      "spread": null
    },
    "cluster": "other"
  },
  {
    "token_id": "20257190540739490630509657713144742134547949967093643458458133445357169845406",
    "question": "Will the New York Knicks win the 2026 NBA Finals?",
    "slug": "will-the-new-york-knicks-win-the-2026-nba-finals",
    "regime": "trend",
    "direction": "YES",
    "confidence": 0.66,
    "position": "medium",
    "quality": 0.675,
    "risk_score": 0.4,
    "reasons": [
      "4h move visible",
      "24h move strong",
      "7d move strong",
      "24h and 7d aligned",
      "liquidity good",
      "cluster=other"
    ],
    "risk_flags": [
      "high_noise",
      "trend_noisy",
      "cooldown_active"
    ],
    "advisory_flags": [
      "high_noise",
      "trend_noisy",
      "cooldown_active"
    ],
    "blocking_flags": [
      "high_noise",
      "trend_noisy"
    ],
    "yes_price": 0.056,
    "no_price": 0.944,
    "liquidity": 205220.19,
    "volume": 10801048.57,
    "chg_1h": -0.0088495575221239,
    "chg_4h": 0.5774647887323945,
    "chg_24h": 0.6969696969696969,
    "chg_7d": 2.1999999999999997,
    "latest_ts": "2026-05-01T13:01:03",
    "features": {
      "token_id": "20257190540739490630509657713144742134547949967093643458458133445357169845406",
      "question": "Will the New York Knicks win the 2026 NBA Finals?",
      "slug": "will-the-new-york-knicks-win-the-2026-nba-finals",
      "yes_price": 0.056,
      "no_price": 0.944,
      "liquidity": 205220.19461,
      "volume": 10801048.566261858,
      "latest_ts": "2026-05-01T13:01:03",
      "history_points": 10887,
      "chg_1h": -0.0088495575221239,
      "chg_4h": 0.5774647887323945,
      "chg_24h": 0.6969696969696969,
      "chg_7d": 2.1999999999999997,
      "rsi_14": 76.23367208282224,
      "volatility": 0.0030364795785862903,
      "trend_slope_4h": -2.4811398575178084e-05,
      "trend_slope_24h": 3.087373085662402e-05,
      "pct_rank_7d": 0.9592616168045831,
      "pct_rank_30d": 0.9882428584550381,
      "noise_score": 3.1171395407496263,
      "hours_to_event": 1450.9825,
      "event_time": "2026-07-01",
      "spread": null
    },
    "cluster": "other"
  },
  {
    "token_id": "98951343420969493497594761179562691809954416596888138302255086663562042936451",
    "question": "Will the Boston Celtics win the 2026 NBA Finals?",
    "slug": "will-the-boston-celtics-win-the-2026-nba-finals",
    "regime": "trend",
    "direction": "NO",
    "confidence": 0.66,
    "position": "medium",
    "quality": 0.675,
    "risk_score": 0.4,
    "reasons": [
      "4h move visible",
      "24h move strong",
      "7d move strong",
      "24h and 7d aligned",
      "liquidity good",
      "cluster=other"
    ],
    "risk_flags": [
      "high_noise",
      "trend_noisy",
      "cooldown_active"
    ],
    "advisory_flags": [
      "high_noise",
      "trend_noisy",
      "cooldown_active"
    ],
    "blocking_flags": [
      "high_noise",
      "trend_noisy"
    ],
    "yes_price": 0.092,
    "no_price": 0.908,
    "liquidity": 166180.95,
    "volume": 12656747.74,
    "chg_1h": 0.0635838150289018,
    "chg_4h": -0.264,
    "chg_24h": -0.38870431893687707,
    "chg_7d": -0.22689075630252098,
    "latest_ts": "2026-05-01T13:01:03",
    "features": {
      "token_id": "98951343420969493497594761179562691809954416596888138302255086663562042936451",
      "question": "Will the Boston Celtics win the 2026 NBA Finals?",
      "slug": "will-the-boston-celtics-win-the-2026-nba-finals",
      "yes_price": 0.092,
      "no_price": 0.908,
      "liquidity": 166180.94561,
      "volume": 12656747.737479348,
      "latest_ts": "2026-05-01T13:01:03",
      "history_points": 10887,
      "chg_1h": 0.0635838150289018,
      "chg_4h": -0.264,
      "chg_24h": -0.38870431893687707,
      "chg_7d": -0.22689075630252098,
      "rsi_14": 58.940567521153184,
      "volatility": 0.0037745207672897694,
      "trend_slope_4h": 3.3817772778402716e-05,
      "trend_slope_24h": -4.85941305668936e-05,
      "pct_rank_7d": 0.03532781667727562,
      "pct_rank_30d": 0.010195646183521631,
      "noise_score": 3.2723809393482717,
      "hours_to_event": 1450.9825,
      "event_time": "2026-07-01",
      "spread": null
    },
    "cluster": "other"
  },
  {
    "token_id": "21929863894047830651599085392978377118642353711084157807549430066031384497667",
    "question": "Will the Cleveland Cavaliers win the 2026 NBA Finals?",
    "slug": "will-the-cleveland-cavaliers-win-the-2026-nba-finals",
    "regime": "trend",
    "direction": "YES",
    "confidence": 0.66,
    "position": "medium",
    "quality": 0.675,
    "risk_score": 0.4,
    "reasons": [
      "4h move visible",
      "24h move strong",
      "7d move strong",
      "4h and 24h aligned",
      "4h and 24h slope aligned",
      "liquidity good",
      "cluster=other"
    ],
    "risk_flags": [
      "high_noise",
      "trend_noisy",
      "cooldown_active"
    ],
    "advisory_flags": [
      "high_noise",
      "trend_noisy",
      "cooldown_active"
    ],
    "blocking_flags": [
      "high_noise",
      "trend_noisy"
    ],
    "yes_price": 0.0425,
    "no_price": 0.9575,
    "liquidity": 108334.15,
    "volume": 11112806.63,
    "chg_1h": 0.024096385542168693,
    "chg_4h": 0.07594936708860767,
    "chg_24h": 0.16438356164383577,
    "chg_7d": -0.13265306122448978,
    "latest_ts": "2026-05-01T13:02:00",
    "features": {
      "token_id": "21929863894047830651599085392978377118642353711084157807549430066031384497667",
      "question": "Will the Cleveland Cavaliers win the 2026 NBA Finals?",
      "slug": "will-the-cleveland-cavaliers-win-the-2026-nba-finals",
      "yes_price": 0.0425,
      "no_price": 0.9575,
      "liquidity": 108334.1549,
      "volume": 11112806.627234034,
      "latest_ts": "2026-05-01T13:02:00",
      "history_points": 10888,
      "chg_1h": 0.024096385542168693,
      "chg_4h": 0.07594936708860767,
      "chg_24h": 0.16438356164383577,
      "chg_7d": -0.13265306122448978,
      "rsi_14": 52.87624125377016,
      "volatility": 0.0034383632874547152,
      "trend_slope_4h": 8.16401856017998e-06,
      "trend_slope_24h": 4.950911943419742e-06,
      "pct_rank_7d": 0.5504295259306395,
      "pct_rank_30d": 0.7002204261572373,
      "noise_score": 3.542901909121541,
      "hours_to_event": 1450.9666666666667,
      "event_time": "2026-07-01",
      "spread": null
    },
    "cluster": "other"
  },
  {
    "token_id": "350977769852917329387037893294763093471844346281449484439085576212613048126",
    "question": "Putin out as President of Russia by December 31, 2026?",
    "slug": "putin-out-before-2027",
    "regime": "mean_revert",
    "direction": "NO",
    "confidence": 0.624,
    "position": "small",
    "quality": 0.61,
    "risk_score": 0.32,
    "reasons": [
      "upper percentile fade setup",
      "RSI extreme",
      "low tradability profile",
      "vNext gate: question_not_whitelisted_v6",
      "cluster=other"
    ],
    "risk_flags": [
      "low_tradability",
      "question_not_whitelisted_v6",
      "cooldown_active"
    ],
    "advisory_flags": [
      "low_tradability",
      "question_not_whitelisted_v6",
      "cooldown_active"
    ],
    "blocking_flags": [
      "low_tradability",
      "question_not_whitelisted_v6"
    ],
    "yes_price": 0.115,
    "no_price": 0.885,
    "liquidity": 208360.12,
    "volume": 4270273.57,
    "chg_1h": 0.0,
    "chg_4h": 0.0,
    "chg_24h": 0.0,
    "chg_7d": 0.0,
    "latest_ts": "2026-05-01T13:01:03",
    "features": {
      "token_id": "350977769852917329387037893294763093471844346281449484439085576212613048126",
      "question": "Putin out as President of Russia by December 31, 2026?",
      "slug": "putin-out-before-2027",
      "yes_price": 0.115,
      "no_price": 0.885,
      "liquidity": 208360.1236,
      "volume": 4270273.573890949,
      "latest_ts": "2026-05-01T13:01:03",
      "history_points": 10887,
      "chg_1h": 0.0,
      "chg_4h": 0.0,
      "chg_24h": 0.0,
      "chg_7d": 0.0,
      "rsi_14": 100.0,
      "volatility": 0.0,
      "trend_slope_4h": 0.0,
      "trend_slope_24h": 0.0,
      "pct_rank_7d": 1.0,
      "pct_rank_30d": 0.9258748966657482,
      "noise_score": 0.0,
      "hours_to_event": 5842.9825,
      "event_time": "2026-12-31",
      "spread": null
    },
    "cluster": "other"
  },
  {
    "token_id": "49500299856831034491021962156746701298730459370557900271970866855042624695770",
    "question": "Will the Oklahoma City Thunder win the 2026 NBA Finals?",
    "slug": "will-the-oklahoma-city-thunder-win-the-2026-nba-finals",
    "regime": "trend",
    "direction": "YES",
    "confidence": 0.6216,
    "position": "small",
    "quality": 0.627,
    "risk_score": 0.4,
    "reasons": [
      "4h move visible",
      "24h move strong",
      "24h and 7d aligned",
      "4h and 24h slope aligned",
      "liquidity good",
      "cluster=other"
    ],
    "risk_flags": [
      "high_noise",
      "trend_noisy"
    ],
    "advisory_flags": [
      "high_noise",
      "trend_noisy"
    ],
    "blocking_flags": [
      "high_noise",
      "trend_noisy"
    ],
    "yes_price": 0.545,
    "no_price": 0.455,
    "liquidity": 273015.81,
    "volume": 9745394.39,
    "chg_1h": 0.038095238095238126,
    "chg_4h": 0.038095238095238126,
    "chg_24h": 0.05825242718446607,
    "chg_7d": 0.05825242718446607,
    "latest_ts": "2026-05-01T13:01:03",
    "features": {
      "token_id": "49500299856831034491021962156746701298730459370557900271970866855042624695770",
      "question": "Will the Oklahoma City Thunder win the 2026 NBA Finals?",
      "slug": "will-the-oklahoma-city-thunder-win-the-2026-nba-finals",
      "yes_price": 0.545,
      "no_price": 0.455,
      "liquidity": 273015.8111,
      "volume": 9745394.391981287,
      "latest_ts": "2026-05-01T13:01:03",
      "history_points": 10887,
      "chg_1h": 0.038095238095238126,
      "chg_4h": 0.038095238095238126,
      "chg_24h": 0.05825242718446607,
      "chg_7d": 0.05825242718446607,
      "rsi_14": 100.0,
      "volatility": 0.002695195122859721,
      "trend_slope_4h": 8.05699287589052e-05,
      "trend_slope_24h": 3.365094150859366e-06,
      "pct_rank_7d": 1.0,
      "pct_rank_30d": 1.0,
      "noise_score": 4.7960542106460835,
      "hours_to_event": 1450.9825,
      "event_time": "2026-07-01",
      "spread": null
    },
    "cluster": "other"
  },
  {
    "token_id": "1755198236548058730692725634969806667163093356894670716555961840777456036471",
    "question": "Will the Anaheim Ducks win the 2026 NHL Stanley Cup?",
    "slug": "will-the-anaheim-ducks-win-the-2026-nhl-stanley-cup",
    "regime": "mean_revert",
    "direction": "NO",
    "confidence": 0.604,
    "position": "small",
    "quality": 0.585,
    "risk_score": 0.32,
    "reasons": [
      "upper percentile fade setup",
      "24h move extended",
      "vNext gate: liquidity_below_vnext_min",
      "cluster=other"
    ],
    "risk_flags": [
      "high_noise",
      "liquidity_below_vnext_min",
      "cooldown_active"
    ],
    "advisory_flags": [
      "high_noise",
      "liquidity_below_vnext_min",
      "cooldown_active"
    ],
    "blocking_flags": [
      "high_noise",
      "liquidity_below_vnext_min"
    ],
    "yes_price": 0.0455,
    "no_price": 0.9545,
    "liquidity": 143537.44,
    "volume": 1244161.94,
    "chg_1h": -0.02150537634408604,
    "chg_4h": 0.857142857142857,
    "chg_24h": -0.9071428571428571,
    "chg_7d": 1.8437499999999998,
    "latest_ts": "2026-05-01T13:01:03",
    "features": {
      "token_id": "1755198236548058730692725634969806667163093356894670716555961840777456036471",
      "question": "Will the Anaheim Ducks win the 2026 NHL Stanley Cup?",
      "slug": "will-the-anaheim-ducks-win-the-2026-nhl-stanley-cup",
      "yes_price": 0.0455,
      "no_price": 0.9545,
      "liquidity": 143537.43773,
      "volume": 1244161.9379199995,
      "latest_ts": "2026-05-01T13:01:03",
      "history_points": 10887,
      "chg_1h": -0.02150537634408604,
      "chg_4h": 0.857142857142857,
      "chg_24h": -0.9071428571428571,
      "chg_7d": 1.8437499999999998,
      "rsi_14": 63.08849338546276,
      "volatility": 0.016362245263299116,
      "trend_slope_4h": 2.396400449943755e-05,
      "trend_slope_24h": 2.7278263999544887e-05,
      "pct_rank_7d": 0.9598981540420115,
      "pct_rank_30d": 0.9884265637916781,
      "noise_score": 3.15426166862236,
      "hours_to_event": 1426.9825,
      "event_time": "2026-06-30",
      "spread": null
    },
    "cluster": "other"
  },
  {
    "token_id": "68803485030073596962715540294172682212192134248970512695855620898253368033218",
    "question": "Will the Vegas Golden Knights win the 2026 NHL Stanley Cup?",
    "slug": "will-the-vegas-golden-knights-win-the-2026-nhl-stanley-cup",
    "regime": "mean_revert",
    "direction": "NO",
    "confidence": 0.604,
    "position": "small",
    "quality": 0.585,
    "risk_score": 0.32,
    "reasons": [
      "upper percentile fade setup",
      "24h move extended",
      "vNext gate: liquidity_below_vnext_min",
      "cluster=other"
    ],
    "risk_flags": [
      "high_noise",
      "liquidity_below_vnext_min",
      "cooldown_active"
    ],
    "advisory_flags": [
      "high_noise",
      "liquidity_below_vnext_min",
      "cooldown_active"
    ],
    "blocking_flags": [
      "high_noise",
      "liquidity_below_vnext_min"
    ],
    "yes_price": 0.1145,
    "no_price": 0.8855,
    "liquidity": 30221.41,
    "volume": 1763650.12,
    "chg_1h": 0.08530805687203799,
    "chg_4h": 0.2245989304812835,
    "chg_24h": -0.7663265306122449,
    "chg_7d": 0.6962962962962963,
    "latest_ts": "2026-05-01T13:02:00",
    "features": {
      "token_id": "68803485030073596962715540294172682212192134248970512695855620898253368033218",
      "question": "Will the Vegas Golden Knights win the 2026 NHL Stanley Cup?",
      "slug": "will-the-vegas-golden-knights-win-the-2026-nhl-stanley-cup",
      "yes_price": 0.1145,
      "no_price": 0.8855,
      "liquidity": 30221.41134,
      "volume": 1763650.1234959923,
      "latest_ts": "2026-05-01T13:02:00",
      "history_points": 10888,
      "chg_1h": 0.08530805687203799,
      "chg_4h": 0.2245989304812835,
      "chg_24h": -0.7663265306122449,
      "chg_7d": 0.6962962962962963,
      "rsi_14": 47.174623594116134,
      "volatility": 0.01867460712303276,
      "trend_slope_4h": 0.00012854447881514814,
      "trend_slope_24h": 5.2854512872064566e-05,
      "pct_rank_7d": 0.9720012726694242,
      "pct_rank_30d": 0.9919177075679647,
      "noise_score": 4.905030082961785,
      "hours_to_event": 1426.9666666666667,
      "event_time": "2026-06-30",
      "spread": null
    },
    "cluster": "other"
  },
  {
    "token_id": "114248353339288476395516704859280406139740194553592209059241667781908210476009",
    "question": "Will the Montreal Canadiens win the 2026 NHL Stanley Cup?",
    "slug": "will-the-montreal-canadiens-win-the-2026-nhl-stanley-cup",
    "regime": "trend",
    "direction": "YES",
    "confidence": 0.6,
    "position": "small",
    "quality": 0.6,
    "risk_score": 0.4,
    "reasons": [
      "4h move visible",
      "24h move strong",
      "7d move strong",
      "24h and 7d aligned",
      "4h and 24h slope aligned",
      "liquidity good",
      "cluster=other"
    ],
    "risk_flags": [
      "high_noise",
      "trend_noisy",
      "cooldown_active"
    ],
    "advisory_flags": [
      "high_noise",
      "trend_noisy",
      "cooldown_active"
    ],
    "blocking_flags": [
      "high_noise",
      "trend_noisy"
    ],
    "yes_price": 0.056,
    "no_price": 0.944,
    "liquidity": 90364.8,
    "volume": 1962152.19,
    "chg_1h": -0.13178294573643412,
    "chg_4h": -0.18840579710144933,
    "chg_24h": 0.5774647887323945,
    "chg_7d": 0.20430107526881724,
    "latest_ts": "2026-05-01T13:02:00",
    "features": {
      "token_id": "114248353339288476395516704859280406139740194553592209059241667781908210476009",
      "question": "Will the Montreal Canadiens win the 2026 NHL Stanley Cup?",
      "slug": "will-the-montreal-canadiens-win-the-2026-nhl-stanley-cup",
      "yes_price": 0.056,
      "no_price": 0.944,
      "liquidity": 90364.79565,
      "volume": 1962152.1920049884,
      "latest_ts": "2026-05-01T13:02:00",
      "history_points": 10888,
      "chg_1h": -0.13178294573643412,
      "chg_4h": -0.18840579710144933,
      "chg_24h": 0.5774647887323945,
      "chg_7d": 0.20430107526881724,
      "rsi_14": 55.55116733075495,
      "volatility": 0.011601128363440622,
      "trend_slope_4h": -8.00788573303337e-05,
      "trend_slope_24h": -8.029533011195443e-06,
      "pct_rank_7d": 0.49793191218580973,
      "pct_rank_30d": 0.7595518001469508,
      "noise_score": 3.9421142982962043,
      "hours_to_event": 1426.9666666666667,
      "event_time": "2026-06-30",
      "spread": null
    },
    "cluster": "other"
  },
  {
    "token_id": "8501497159083948713316135768103773293754490207922884688769443031624417212426",
    "question": "Russia-Ukraine Ceasefire before GTA VI?",
    "slug": "russia-ukraine-ceasefire-before-gta-vi-554",
    "regime": "trend",
    "direction": "YES",
    "confidence": 0.6,
    "position": "small",
    "quality": 0.6,
    "risk_score": 0.4,
    "reasons": [
      "4h move visible",
      "24h move strong",
      "7d move strong",
      "24h and 7d aligned",
      "4h and 24h slope aligned",
      "liquidity good",
      "cluster=gta_vi"
    ],
    "risk_flags": [
      "high_noise",
      "trend_noisy",
      "cooldown_active"
    ],
    "advisory_flags": [
      "high_noise",
      "trend_noisy",
      "cooldown_active"
    ],
    "blocking_flags": [
      "high_noise",
      "trend_noisy"
    ],
    "yes_price": 0.59,
    "no_price": 0.41,
    "liquidity": 55067.78,
    "volume": 1635983.52,
    "chg_1h": 0.008547008547008555,
    "chg_4h": 0.03508771929824565,
    "chg_24h": 0.10280373831775688,
    "chg_7d": 0.1238095238095237,
    "latest_ts": "2026-05-01T13:02:00",
    "features": {
      "token_id": "8501497159083948713316135768103773293754490207922884688769443031624417212426",
      "question": "Russia-Ukraine Ceasefire before GTA VI?",
      "slug": "russia-ukraine-ceasefire-before-gta-vi-554",
      "yes_price": 0.59,
      "no_price": 0.41,
      "liquidity": 55067.7819,
      "volume": 1635983.522224053,
      "latest_ts": "2026-05-01T13:02:00",
      "history_points": 10888,
      "chg_1h": 0.008547008547008555,
      "chg_4h": 0.03508771929824565,
      "chg_24h": 0.10280373831775688,
      "chg_7d": 0.1238095238095237,
      "rsi_14": 60.35997856758727,
      "volatility": 0.001503978229529961,
      "trend_slope_4h": 3.157808398950135e-05,
      "trend_slope_24h": 8.878924506462282e-05,
      "pct_rank_7d": 0.9984091632198536,
      "pct_rank_30d": 0.9995407788390889,
      "noise_score": 4.795876831798896,
      "hours_to_event": 2170.9666666666667,
      "event_time": "2026-07-31",
      "spread": null
    },
    "cluster": "gta_vi"
  },
  {
    "token_id": "90435811253665578014957380826505992530054077692143838383981805324273750424057",
    "question": "Will Jesus Christ return before GTA VI?",
    "slug": "will-jesus-christ-return-before-gta-vi-665",
    "regime": "mean_revert",
    "direction": "NO",
    "confidence": 0.564,
    "position": "small",
    "quality": 0.535,
    "risk_score": 0.32,
    "reasons": [
      "upper percentile fade setup",
      "vNext gate: question_blocklisted_v6",
      "cluster=gta_vi"
    ],
    "risk_flags": [
      "question_blocklisted_v6",
      "cooldown_active"
    ],
    "advisory_flags": [
      "question_blocklisted_v6",
      "cooldown_active"
    ],
    "blocking_flags": [
      "question_blocklisted_v6"
    ],
    "yes_price": 0.485,
    "no_price": 0.515,
    "liquidity": 350772.23,
    "volume": 11166059.23,
    "chg_1h": 0.0,
    "chg_4h": 0.0,
    "chg_24h": 0.02105263157894739,
    "chg_7d": 0.0,
    "latest_ts": "2026-05-01T13:01:03",
    "features": {
      "token_id": "90435811253665578014957380826505992530054077692143838383981805324273750424057",
      "question": "Will Jesus Christ return before GTA VI?",
      "slug": "will-jesus-christ-return-before-gta-vi-665",
      "yes_price": 0.485,
      "no_price": 0.515,
      "liquidity": 350772.2312,
      "volume": 11166059.229244957,
      "latest_ts": "2026-05-01T13:01:03",
      "history_points": 10887,
      "chg_1h": 0.0,
      "chg_4h": 0.0,
      "chg_24h": 0.02105263157894739,
      "chg_7d": 0.0,
      "rsi_14": 36.360821826446546,
      "volatility": 0.0,
      "trend_slope_4h": 0.0,
      "trend_slope_24h": 0.0,
      "pct_rank_7d": 0.9875875238701464,
      "pct_rank_30d": 0.9964177459355195,
      "noise_score": 0.0,
      "hours_to_event": 2170.9825,
      "event_time": "2026-07-31",
      "spread": null
    },
    "cluster": "gta_vi"
  }
]